Sheilai/__init__.py
Sheilai/main.py
Sheilai/train.py
sheilai/__init__.py
sheilai/main.py
sheilai/sheilai.py
sheilai/train.py
sheila_ai-0.1.3.dist-info/LICENSE
sheila_ai-0.1.3.dist-info/METADATA
sheila_ai-0.1.3.dist-info/WHEEL
sheila_ai-0.1.3.dist-info/top_level.txt
sheila_ai-0.1.3.dist-info/RECORD
