Metadata-Version: 2.1
Name: sheila-ai
Version: 0.1.3
Summary: Toolkit for building Pytorch Classifiers.
Home-page: https://github.com/Lill-E-Software/SheilAI
Author: jackfhession
Author-email: 
License: MIT
Platform: UNKNOWN
Classifier: Programming Language :: Python :: 3
Classifier: License :: OSI Approved :: MIT License
Classifier: Operating System :: OS Independent
Requires-Python: >=3.6
License-File: LICENSE
Requires-Dist: nltk
Requires-Dist: numpy
Requires-Dist: torch
